Metadata-Version: 2.1
Name: shishua
Version: 0.2.0
Summary: SHISHUA: The fastest PRNG. A seedrandom-compatible random number generator.
Home-page: https://github.com/espadrine/shishua-python
Author: Thaddée Tyl
Author-email: thaddee.tyl@gmail.com
License: UNKNOWN
Project-URL: Bug Tracker, https://github.com/espadrine/shishua-python/issues
Platform: UNKNOWN
Classifier: Programming Language :: Python :: 3
Classifier: License :: CC0 1.0 Universal (CC0 1.0) Public Domain Dedication
Classifier: Operating System :: Microsoft :: Windows
Classifier: Operating System :: POSIX
Classifier: Operating System :: Unix
Classifier: Operating System :: MacOS
Classifier: Development Status :: 5 - Production/Stable
Classifier: Intended Audience :: Developers
Classifier: Topic :: Software Development
Classifier: Topic :: Scientific/Engineering
Requires-Python: >=3.6
License-File: LICENSE
